pygbm/__init__.py
pygbm/base.py
pygbm/cli.py
pygbm/simulator.py
pygbm/version.py
pygbm_yhuo-1.0.0.post2.dist-info/licenses/LICENSE
pygbm_yhuo-1.0.0.post2.dist-info/METADATA
pygbm_yhuo-1.0.0.post2.dist-info/WHEEL
pygbm_yhuo-1.0.0.post2.dist-info/entry_points.txt
pygbm_yhuo-1.0.0.post2.dist-info/top_level.txt
pygbm_yhuo-1.0.0.post2.dist-info/RECORD
