Metadata-Version: 2.4
Name: pygbm-yhuo
Version: 1.0.0.post2
Summary: A Python pckage for stimulating Geometric Brownian Motion
Author-email: Yuhao Huo <martinyuhaohuo@gmail.com>
License: MIT License
Project-URL: Documentation, https://your-readthedocs-url-here
Project-URL: Source, https://github.com/martinyuhaohuo/GBM
Project-URL: Issues, https://github.com/martinyuhaohuo/GBM/issues
Keywords: simulation,GBM,physics
Classifier: License :: OSI Approved :: MIT License
Classifier: Programming Language :: Python :: 3
Classifier: Topic :: Software Development :: Libraries
Requires-Python: >=3.9
License-File: LICENSE
Requires-Dist: numpy
Requires-Dist: matplotlib
Requires-Dist: argparse
Dynamic: license-file
